<?xml version="1.0" encoding="UTF-8"?>	
<databaseChangeLog
	xmlns="http://www.liquibase.org/xml/ns/dbchangelog"
	xmlns:xsi="http://www.w3.org/2001/XMLSchema-instance"
	xmlns:ext="http://www.liquibase.org/xml/ns/dbchangelog-ext"
	xmlns:pro="http://www.liquibase.org/xml/ns/pro"
	xsi:schemaLocation="http://www.liquibase.org/xml/ns/dbchangelog
		http://www.liquibase.org/xml/ns/dbchangelog/dbchangelog-4.0.xsd
		http://www.liquibase.org/xml/ns/dbchangelog-ext http://www.liquibase.org/xml/ns/dbchangelog/dbchangelog-ext.xsd
		http://www.liquibase.org/xml/ns/pro http://www.liquibase.org/xml/ns/pro/liquibase-pro-4.0.xsd">
		
	<changeSet id="spring-apisecurity-1" author="anchtun1212">
		<sql>
			DROP TABLE IF EXISTS jdbc_customer;
			CREATE TABLE jdbc_customer ( customer_id INT generated BY DEFAULT AS IDENTITY PRIMARY key, full_name VARCHAR(50), email VARCHAR(50) NOT NULL UNIQUE, birth_date DATE, gender VARCHAR(50) );
		</sql>
		<rollback>
			drop table jdbc_customer;
		</rollback>
	</changeSet>
	<changeSet id="spring-apisecurity-2" author="anchtun1212">
		<sql>
			INSERT INTO jdbc_customer (full_name, email, birth_date, gender) VALUES ('Maggee Donald', 'mdonald0@marriott.com', '1987-06-13', 'F');
			INSERT INTO jdbc_customer (full_name, email, birth_date, gender) VALUES ('Arni Sturch', 'asturch1@bbb.org', '1981-05-02', 'F');
			INSERT INTO jdbc_customer (full_name, email, birth_date, gender) VALUES ('Abbot Angel', 'aangel2@ihg.com', '1984-12-23', 'M');
 			INSERT INTO jdbc_customer (full_name, email, birth_date, gender) VALUES ('Georgeta Drackford', 'gdrackford3@nature.com', '1993-11-02', 'F');
			INSERT INTO jdbc_customer (full_name, email, birth_date, gender) VALUES ('Marin Pollendine', 'mpollendine4@reddit.com', '1999-10-21', 'F');
			INSERT INTO jdbc_customer (full_name, email, birth_date, gender) VALUES ( 'Lloyd Garber', 'lgarber5@wsj.com', '1991-08-28', 'M' );
			INSERT INTO jdbc_customer (full_name, email, birth_date, gender) VALUES ( 'Savina Manwaring', 'smanwaring6@sfgate.com', '1996-01-03', 'F' );
			INSERT INTO jdbc_customer (full_name, email, birth_date, gender) VALUES ( 'Daniel Hansard', 'dhansard7@rediff.com', '1986-09-18', 'M' );
			INSERT INTO jdbc_customer (full_name, email, birth_date, gender) VALUES ( 'Patricia Titherington', 'ptitherington8@ehow.com', '1994-07-12', 'F' );
			INSERT INTO jdbc_customer (full_name, email, birth_date, gender) VALUES ( 'Meta Boleyn', 'mboleyn9@ox.ac.uk', '1982-05-20', 'F' );
		</sql>
	</changeSet>
	<changeSet id="spring-apisecurity-3" author="anchtun1212">
		<sql>
			DROP TABLE IF EXISTS jdbc_merchant;
			CREATE TABLE jdbc_merchant ( merchant_id INT generated BY DEFAULT AS IDENTITY PRIMARY key, merchant_name VARCHAR(50), email VARCHAR(50), description text );
		</sql>
		<rollback>
			drop table jdbc_merchant;
		</rollback>
	</changeSet>
	<changeSet id="spring-apisecurity-4" author="anchtun1212">
		<sql>
			INSERT INTO jdbc_merchant (merchant_name, email, description) VALUES ( 'Heathcote Inc', 'rgilkes0@e-recht24.de', 'Maecenas tristique, est et tempus semper, est quam pharetra magna, ac consequat metus sapien ut nunc. Vestibulum ante ipsum primis in faucibus orci luctus et ultrices posuere cubilia Curae; Mauris viverra diam vitae quam. Suspendisse potenti.' );
			INSERT INTO jdbc_merchant (merchant_name, email, description) VALUES ( 'Volkman, Roberts and Dietrich', 'ebenstead1@auda.org.au', 'Nullam porttitor lacus at turpis. Donec posuere metus vitae ipsum. Aliquam non mauris.' );
			INSERT INTO jdbc_merchant (merchant_name, email, description) VALUES ( 'Moore LLC', 'mtillman2@house.gov', NULL );
			INSERT INTO jdbc_merchant (merchant_name, email, description) VALUES ( 'Purdy and Sons', 'jhambelton3@wikipedia.org', NULL );
			INSERT INTO jdbc_merchant (merchant_name, email, description) VALUES ( 'Kuhic-Parisian', 'dmccreery4@wix.com', 'Curabitur at ipsum ac tellus semper interdum. Mauris ullamcorper purus sit amet nulla. Quisque arcu libero, rutrum ac, lobortis vel, dapibus at, diam.' );
			INSERT INTO jdbc_merchant (merchant_name, email, description) VALUES ( 'Greenfelder-Emard', 'eclara5@webeden.co.uk', 'Duis aliquam convallis nunc. Proin at turpis a pede posuere nonummy. Integer non velit.' );
			INSERT INTO jdbc_merchant (merchant_name, email, description) VALUES ( 'Armstrong and Sons', 'mhartle6@phoca.cz', NULL );
			INSERT INTO jdbc_merchant (merchant_name, email, description) VALUES ( 'Goyette-Pollich', 'vblowin7@jiathis.com', 'In quis justo. Maecenas rhoncus aliquam lacus. Morbi quis tortor id nulla ultrices aliquet.' );
			INSERT INTO jdbc_merchant (merchant_name, email, description) VALUES ( 'Yundt Group', 'larnli8@pen.io', 'Morbi porttitor lorem id ligula. Suspendisse ornare consequat lectus. In est risus, auctor sed, tristique in, tempus sit amet, sem.' );
			INSERT INTO jdbc_merchant (merchant_name, email, description) VALUES ( 'Wintheiser-Cummerata', 'cbartzen9@archive.org', NULL );
		</sql>
	</changeSet>
	<changeSet id="spring-apisecurity-5" author="anchtun1212">
		<sql>
			DROP TABLE IF EXISTS jpa_customer;
			CREATE TABLE jpa_customer ( customer_id INT generated BY DEFAULT AS IDENTITY PRIMARY key, full_name VARCHAR(50), email VARCHAR(50) NOT NULL UNIQUE, birth_date DATE, gender VARCHAR(50) );
		</sql>
		<rollback>
			drop table jpa_customer;
		</rollback>
	</changeSet>
	<changeSet id="spring-apisecurity-6" author="anchtun1212">
		<sql>
			INSERT INTO jpa_customer (full_name, email, birth_date, gender) VALUES ( 'Maggee Donald', 'mdonald0@marriott.com', '1987-06-13', 'F' );
			INSERT INTO jpa_customer (full_name, email, birth_date, gender) VALUES ( 'Arni Sturch', 'asturch1@bbb.org', '1981-05-02', 'F' );
			INSERT INTO jpa_customer (full_name, email, birth_date, gender) VALUES ( 'Abbot Angel', 'aangel2@ihg.com', '1984-12-23', 'M' );
			INSERT INTO jpa_customer (full_name, email, birth_date, gender) VALUES ( 'Georgeta Drackford', 'gdrackford3@nature.com', '1993-11-02', 'F' );
			INSERT INTO jpa_customer (full_name, email, birth_date, gender) VALUES ( 'Marin Pollendine', 'mpollendine4@reddit.com', '1999-10-21', 'F' );
			INSERT INTO jpa_customer (full_name, email, birth_date, gender) VALUES ( 'Lloyd Garber', 'lgarber5@wsj.com', '1991-08-28', 'M' );
			INSERT INTO jpa_customer (full_name, email, birth_date, gender) VALUES ( 'Savina Manwaring', 'smanwaring6@sfgate.com', '1996-01-03', 'F' );
			INSERT INTO jpa_customer (full_name, email, birth_date, gender) VALUES ( 'Daniel Hansard', 'dhansard7@rediff.com', '1986-09-18', 'M' );
			INSERT INTO jpa_customer (full_name, email, birth_date, gender) VALUES ( 'Patricia Titherington', 'ptitherington8@ehow.com', '1994-07-12', 'F' );
			INSERT INTO jpa_customer (full_name, email, birth_date, gender) VALUES ( 'Meta Boleyn', 'mboleyn9@ox.ac.uk', '1982-05-20', 'F' );
		</sql>
	</changeSet>
</databaseChangeLog>	